satdatagen/GroundLocation.py
satdatagen/M90.py
satdatagen/TimeRange.py
satdatagen/__init__.py
satdatagen/helpers.py
satdatagen/object_sizes.json
satdatagen/sizes.py
satdatagen-1.0.1.dist-info/METADATA
satdatagen-1.0.1.dist-info/WHEEL
satdatagen-1.0.1.dist-info/licenses/LICENSE
satdatagen-1.0.1.dist-info/RECORD
