Metadata-Version: 2.3
Name: satdatagen
Version: 1.0.1
Summary: A Python package to generate datasets for satellite tasking schedulers.
Project-URL: Homepage, https://github.com/ahgolden/satdatagen
Project-URL: Issues, https://github.com/ahgolden/satdatagen/issues
Author-email: Adina Golden <adinag@alum.mit.edu>
License-File: LICENSE
Classifier: License :: OSI Approved :: MIT License
Classifier: Operating System :: OS Independent
Classifier: Programming Language :: Python :: 3
Requires-Python: >=3.8
Requires-Dist: astropy
Requires-Dist: datetime
Requires-Dist: numpy
Requires-Dist: openmeteo-requests
Requires-Dist: requests
Requires-Dist: sgp4
